Workbook

Sheet Sales_Data
A1: Order ID | B1: Customer ID | C1: Date | D1: Product | E1: Category | F1: Quantity | G1: Price | H1: Revenue | I1: Region | J1: Membership Type
A2: ORD001 | B2: ="CUST"&TEXT(RANDBETWEEN(1,200),"000") -> CUST035 | C2: =DATE(2025,1,1)+RANDBETWEEN(0,364) -> 45964 | D2: Jacket | E2: Outwear | F2: =RANDBETWEEN(1,10) -> 3 | G2: 120 | H2: =F2*G2 -> 360 | I2: East | J2: =VLOOKUP(B2,Customer_Data!$A:$D,4,FALSE) -> Silver
A3: ORD002 | B3: ="CUST"&TEXT(RANDBETWEEN(1,200),"000") -> CUST082 | C3: =DATE(2025,1,1)+RANDBETWEEN(0,364) -> 45991 | D3: Jacket | E3: Outwear | F3: =RANDBETWEEN(1,10) -> 5 | G3: 120 | H3: =F3*G3 -> 600 | I3: South | J3: =VLOOKUP(B3,Customer_Data!$A:$D,4,FALSE) -> Regular
A4: ORD003 | B4: ="CUST"&TEXT(RANDBETWEEN(1,200),"000") -> CUST191 | C4: =DATE(2025,1,1)+RANDBETWEEN(0,364) -> 45848 | D4: Jeans | E4: Bottoms | F4: =RANDBETWEEN(1,10) -> 5 | G4: 60 | H4: =F4*G4 -> 300 | I4: West | J4: =VLOOKUP(B4,Customer_Data!$A:$D,4,FALSE) -> Regular
A5: ORD004 | B5: ="CUST"&TEXT(RANDBETWEEN(1,200),"000") -> CUST155 | C5: =DATE(2025,1,1)+RANDBETWEEN(0,364) -> 45936 | D5: Sneakers | E5: Footwear | F5: =RANDBETWEEN(1,10) -> 3 | G5: 90 | H5: =F5*G5 -> 270 | I5: West | J5: =VLOOKUP(B5,Customer_Data!$A:$D,4,FALSE) -> Silver
A6: ORD005 | B6: ="CUST"&TEXT(RANDBETWEEN(1,200),"000") -> CUST010 | C6: =DATE(2025,1,1)+RANDBETWEEN(0,364) -> 45676 | D6: Jeans | E6: Bottoms | F6: =RANDBETWEEN(1,10) -> 1 | G6: 60 | H6: =F6*G6 -> 60 | I6: East | J6: =VLOOKUP(B6,Customer_Data!$A:$D,4,FALSE) -> Regular
A7: ORD006 | B7: ="CUST"&TEXT(RANDBETWEEN(1,200),"000") -> CUST068 | C7: =DATE(2025,1,1)+RANDBETWEEN(0,364) -> 45879 | D7: Dress | E7: Dresses | F7: =RANDBETWEEN(1,10) -> 4 | G7: 80 | H7: =F7*G7 -> 320 | I7: East | J7: =VLOOKUP(B7,Customer_Data!$A:$D,4,FALSE) -> Regular
A8: ORD007 | B8: ="CUST"&TEXT(RANDBETWEEN(1,200),"000") -> CUST064 | C8: =DATE(2025,1,1)+RANDBETWEEN(0,364) -> 45765 | D8: Dress | E8: Dresses | F8: =RANDBETWEEN(1,10) -> 4 | G8: 80 | H8: =F8*G8 -> 320 | I8: South | J8: =VLOOKUP(B8,Customer_Data!$A:$D,4,FALSE) -> Regular
A9: ORD008 | B9: ="CUST"&TEXT(RANDBETWEEN(1,200),"000") -> CUST076 | C9: =DATE(2025,1,1)+RANDBETWEEN(0,364) -> 45937 | D9: Jacket | E9: Outwear | F9: =RANDBETWEEN(1,10) -> 10 | G9: 120 | H9: =F9*G9 -> 1200 | I9: East | J9: =VLOOKUP(B9,Customer_Data!$A:$D,4,FALSE) -> Silver
A10: ORD009 | B10: ="CUST"&TEXT(RANDBETWEEN(1,200),"000") -> CUST080 | C10: =DATE(2025,1,1)+RANDBETWEEN(0,364) -> 45828 | D10: Sneakers | E10: Footwear | F10: =RANDBETWEEN(1,10) -> 3 | G10: 90 | H10: =F10*G10 -> 270 | I10: West | J10: =VLOOKUP(B10,Customer_Data!$A:$D,4,FALSE) -> Gold
A11: ORD010 | B11: ="CUST"&TEXT(RANDBETWEEN(1,200),"000") -> CUST082 | C11: =DATE(2025,1,1)+RANDBETWEEN(0,364) -> 45667 | D11: Jeans | E11: Bottoms | F11: =RANDBETWEEN(1,10) -> 10 | G11: 60 | H11: =F11*G11 -> 600 | I11: South | J11: =VLOOKUP(B11,Customer_Data!$A:$D,4,FALSE) -> Regular
A12: ORD011 | B12: ="CUST"&TEXT(RANDBETWEEN(1,200),"000") -> CUST084 | C12: =DATE(2025,1,1)+RANDBETWEEN(0,364) -> 45789 | D12: Tshirt | E12: Tops | F12: =RANDBETWEEN(1,10) -> 3 | G12: 25 | H12: =F12*G12 -> 75 | I12: South | J12: =VLOOKUP(B12,Customer_Data!$A:$D,4,FALSE) -> Regular
A13: ORD012 | B13: ="CUST"&TEXT(RANDBETWEEN(1,200),"000") -> CUST047 | C13: =DATE(2025,1,1)+RANDBETWEEN(0,364) -> 45894 | D13: Tshirt | E13: Tops | F13: =RANDBETWEEN(1,10) -> 1 | G13: 25 | H13: =F13*G13 -> 25 | I13: East | J13: =VLOOKUP(B13,Customer_Data!$A:$D,4,FALSE) -> Regular
... A1001: ORD1000 | B1001: ="CUST"&TEXT(RANDBETWEEN(1,200),"000") -> CUST197 | C1001: =DATE(2025,1,1)+RANDBETWEEN(0,364) -> 45765 | D1001: Dress | E1001: Dresses | F1001: =RANDBETWEEN(1,10) -> 8 | G1001: 80 | H1001: =F1001*G1001 -> 640 | I1001: North | J1001: =VLOOKUP(B1001,Customer_Data!$A:$D,4,FALSE) -> Silver

Sheet Customer_Data
A1: Customer ID | B1: Customer Name | C1: Region | D1: Membership Type
A2: CUST001 | B2: {=INDEX($F$2:$F$16,RANDBETWEEN(1,15)) & " " & INDEX($G$2:$G$16,RANDBETWEEN(1,15))} -> Mia Miller | C2: North | D2: Regular | F2: James | G2: Smith
A3: CUST002 | B3: {=INDEX($F$2:$F$16,RANDBETWEEN(1,15)) & " " & INDEX($G$2:$G$16,RANDBETWEEN(1,15))} -> Mia Smith | C3: East | D3: Regular | F3: Olivia | G3: Johnson
A4: CUST003 | B4: {=INDEX($F$2:$F$16,RANDBETWEEN(1,15)) & " " & INDEX($G$2:$G$16,RANDBETWEEN(1,15))} -> Emma Miller | C4: North | D4: Regular | F4: Michael | G4: Brown
A5: CUST004 | B5: {=INDEX($F$2:$F$16,RANDBETWEEN(1,15)) & " " & INDEX($G$2:$G$16,RANDBETWEEN(1,15))} -> Amara Miller | C5: East | D5: Regular | F5: Sophia | G5: Williams
A6: CUST005 | B6: {=INDEX($F$2:$F$16,RANDBETWEEN(1,15)) & " " & INDEX($G$2:$G$16,RANDBETWEEN(1,15))} -> Chris Thomas | C6: West | D6: Regular | F6: Daniel | G6: Jones
A7: CUST006 | B7: {=INDEX($F$2:$F$16,RANDBETWEEN(1,15)) & " " & INDEX($G$2:$G$16,RANDBETWEEN(1,15))} -> Chris Moore | C7: North | D7: Regular | F7: Emma | G7: Garcia
A8: CUST007 | B8: {=INDEX($F$2:$F$16,RANDBETWEEN(1,15)) & " " & INDEX($G$2:$G$16,RANDBETWEEN(1,15))} -> John Davis | C8: West | D8: Regular | F8: David | G8: Miller
A9: CUST008 | B9: {=INDEX($F$2:$F$16,RANDBETWEEN(1,15)) & " " & INDEX($G$2:$G$16,RANDBETWEEN(1,15))} -> Sophia Moore | C9: West | D9: Regular | F9: Ava | G9: Davis
A10: CUST009 | B10: {=INDEX($F$2:$F$16,RANDBETWEEN(1,15)) & " " & INDEX($G$2:$G$16,RANDBETWEEN(1,15))} -> Olivia Anderson | C10: South | D10: Regular | F10: John | G10: Wilson
A11: CUST010 | B11: {=INDEX($F$2:$F$16,RANDBETWEEN(1,15)) & " " & INDEX($G$2:$G$16,RANDBETWEEN(1,15))} -> James Smith | C11: South | D11: Regular | F11: Isabella | G11: Anderson
A12: CUST011 | B12: {=INDEX($F$2:$F$16,RANDBETWEEN(1,15)) & " " & INDEX($G$2:$G$16,RANDBETWEEN(1,15))} -> James Wilson | C12: South | D12: Regular | F12: Chris | G12: Thomas
A13: CUST012 | B13: {=INDEX($F$2:$F$16,RANDBETWEEN(1,15)) & " " & INDEX($G$2:$G$16,RANDBETWEEN(1,15))} -> Noah Jones | C13: West | D13: Regular | F13: Mia | G13: Taylor
... A16: CUST015 | B16: {=INDEX($F$2:$F$16,RANDBETWEEN(1,15)) & " " & INDEX($G$2:$G$16,RANDBETWEEN(1,15))} -> Noah Anderson | C16: North | D16: Silver | F16: Noah | G16: Jackson
A17: CUST016 | B17: {=INDEX($F$2:$F$16,RANDBETWEEN(1,15)) & " " & INDEX($G$2:$G$16,RANDBETWEEN(1,15))} -> Sophia Smith | C17: North | D17: Silver
A18: CUST017 | B18: {=INDEX($F$2:$F$16,RANDBETWEEN(1,15)) & " " & INDEX($G$2:$G$16,RANDBETWEEN(1,15))} -> John Moore | C18: North | D18: Silver
A19: CUST018 | B19: {=INDEX($F$2:$F$16,RANDBETWEEN(1,15)) & " " & INDEX($G$2:$G$16,RANDBETWEEN(1,15))} -> Isabella Anderson | C19: South | D19: Gold
A20: CUST019 | B20: {=INDEX($F$2:$F$16,RANDBETWEEN(1,15)) & " " & INDEX($G$2:$G$16,RANDBETWEEN(1,15))} -> David Davis | C20: East | D20: Gold
A21: CUST020 | B21: {=INDEX($F$2:$F$16,RANDBETWEEN(1,15)) & " " & INDEX($G$2:$G$16,RANDBETWEEN(1,15))} -> Mia Thomas | C21: East | D21: Gold
A22: CUST021 | B22: {=INDEX($F$2:$F$16,RANDBETWEEN(1,15)) & " " & INDEX($G$2:$G$16,RANDBETWEEN(1,15))} -> Isabella Garcia | C22: West | D22: Regular
A23: CUST022 | B23: {=INDEX($F$2:$F$16,RANDBETWEEN(1,15)) & " " & INDEX($G$2:$G$16,RANDBETWEEN(1,15))} -> Amara Wilson | C23: South | D23: Regular
A24: CUST023 | B24: {=INDEX($F$2:$F$16,RANDBETWEEN(1,15)) & " " & INDEX($G$2:$G$16,RANDBETWEEN(1,15))} -> Noah Williams | C24: East | D24: Regular
A25: CUST024 | B25: {=INDEX($F$2:$F$16,RANDBETWEEN(1,15)) & " " & INDEX($G$2:$G$16,RANDBETWEEN(1,15))} -> John Martin | C25: East | D25: Regular
A26: CUST025 | B26: {=INDEX($F$2:$F$16,RANDBETWEEN(1,15)) & " " & INDEX($G$2:$G$16,RANDBETWEEN(1,15))} -> John Wilson | C26: East | D26: Regular
A27: CUST026 | B27: {=INDEX($F$2:$F$16,RANDBETWEEN(1,15)) & " " & INDEX($G$2:$G$16,RANDBETWEEN(1,15))} -> James Jackson | C27: West | D27: Regular
A28: CUST027 | B28: {=INDEX($F$2:$F$16,RANDBETWEEN(1,15)) & " " & INDEX($G$2:$G$16,RANDBETWEEN(1,15))} -> Isabella Thomas | C28: West | D28: Regular
... A201: CUST200 | B201: {=INDEX($F$2:$F$16,RANDBETWEEN(1,15)) & " " & INDEX($G$2:$G$16,RANDBETWEEN(1,15))} -> Mia Johnson | C201: East | D201: Gold

Sheet Pivot_Analysis
A3: Row Labels | B3: Sum of Revenue | D3: Row Labels | E3: Sum of Revenue | G3: Row Labels | H3: Sum of Revenue | J3: Sum of Revenue | K3: Column Labels
A4: Dress | B4: 93040 | D4: Gold | E4: 72305 | G4: East | H4: 134720 | J4: Row Labels | K4: Gold | L4: Regular | M4: Silver | N4: Grand Total
A5: Jacket | B5: 139920 | D5: Regular | E5: 248295 | G5: North | H5: 91905 | J5: Dress | K5: 17360 | L5: 51760 | M5: 23920 | N5: 93040
A6: Jeans | B6: 70440 | D6: Silver | E6: 115430 | G6: South | H6: 90390 | J6: Jacket | K6: 25200 | L6: 74880 | M6: 39840 | N6: 139920
A7: Sneakers | B7: 105930 | D7: Grand Total | E7: 436030 | G7: West | H7: 119015 | J7: Jeans | K7: 11040 | L7: 41820 | M7: 17580 | N7: 70440
A8: Tshirt | B8: 26700 | G8: Grand Total | H8: 436030 | J8: Sneakers | K8: 15480 | L8: 62010 | M8: 28440 | N8: 105930
A9: Grand Total | B9: 436030 | J9: Tshirt | K9: 3225 | L9: 17825 | M9: 5650 | N9: 26700
J10: Grand Total | K10: 72305 | L10: 248295 | M10: 115430 | N10: 436030

Sheet Dashboard

Sheet Insights
A1: Project 3 - Key Business Insight
A2: Total Revenue Generated : $436,030
A3: 1. Product Performance – Jackets Lead Revenue
A4: Jackets generated the highest total revenue ($139,920), indicating strong demand and higher pricing power compared to other product categories.
A5: Business Implication: Outerwear should remain a strategic focus for inventory planning and promotional efforts.
A7: 2. Membership Revenue Distribution – Regular Members Dominate
A8: Regular membership customers generated the highest total revenue ($248,295), outperforming Silver and Gold tiers.
A9: Business Implication: Revenue growth is currently driven by customer volume rather than premium-tier spending.
A11: 3. Regional Performance – East Region Leads
A12: The East region recorded the highest revenue contribution ($134,720), outperforming other regions.
A13: Business Implication: The East region represents a key market for sustained growth and targeted marketing investment.
A15: 4. Cross-Segment Insight – Regular Members Drive Jacket Sales
... A20: Given that Regular members drive both overall revenue and high-value product purchases, the company could improve long-term profitability by strengthening loyalty incentives that encourage upgrades to Silver and Gold membership tiers.
